{
  "symbol": "603016",
  "data": [
    {
      "日期": "2025-03-28",
      "股票代码": "603016",
      "开盘": 29.55,
      "收盘": 29.34,
      "最高": 29.98,
      "最低": 29.25,
      "成交量": 13479,
      "成交额": 40459175.0,
      "振幅": 2.47,
      "涨跌幅": -0.91,
      "涨跌额": -0.27,
      "换手率": 0.91
    },
    {
      "日期": "2025-03-31",
      "股票代码": "603016",
      "开盘": 28.97,
      "收盘": 28.42,
      "最高": 28.97,
      "最低": 28.19,
      "成交量": 15739,
      "成交额": 45491558.0,
      "振幅": 2.66,
      "涨跌幅": -3.14,
      "涨跌额": -0.92,
      "换手率": 1.06
    },
    {
      "日期": "2025-04-01",
      "股票代码": "603016",
      "开盘": 28.34,
      "收盘": 28.76,
      "最高": 29.34,
      "最低": 28.34,
      "成交量": 13579,
      "成交额": 39857617.0,
      "振幅": 3.52,
      "涨跌幅": 1.2,
      "涨跌额": 0.34,
      "换手率": 0.92
    },
    {
      "日期": "2025-04-02",
      "股票代码": "603016",
      "开盘": 28.74,
      "收盘": 29.01,
      "最高": 29.04,
      "最低": 28.49,
      "成交量": 8035,
      "成交额": 23538610.0,
      "振幅": 1.91,
      "涨跌幅": 0.87,
      "涨跌额": 0.25,
      "换手率": 0.54
    },
    {
      "日期": "2025-04-03",
      "股票代码": "603016",
      "开盘": 28.77,
      "收盘": 28.31,
      "最高": 29.1,
      "最低": 28.0,
      "成交量": 13284,
      "成交额": 38457803.0,
      "振幅": 3.79,
      "涨跌幅": -2.41,
      "涨跌额": -0.7,
      "换手率": 0.9
    },
    {
      "日期": "2025-04-07",
      "股票代码": "603016",
      "开盘": 26.08,
      "收盘": 25.43,
      "最高": 27.1,
      "最低": 25.43,
      "成交量": 9288,
      "成交额": 24267116.0,
      "振幅": 5.9,
      "涨跌幅": -10.17,
      "涨跌额": -2.88,
      "换手率": 0.63
    },
    {
      "日期": "2025-04-08",
      "股票代码": "603016",
      "开盘": 23.75,
      "收盘": 23.58,
      "最高": 25.33,
      "最低": 22.85,
      "成交量": 35553,
      "成交额": 85307992.0,
      "振幅": 9.75,
      "涨跌幅": -7.27,
      "涨跌额": -1.85,
      "换手率": 2.4
    },
    {
      "日期": "2025-04-09",
      "股票代码": "603016",
      "开盘": 22.36,
      "收盘": 24.21,
      "最高": 24.5,
      "最低": 21.6,
      "成交量": 32073,
      "成交额": 75514063.0,
      "振幅": 12.3,
      "涨跌幅": 2.67,
      "涨跌额": 0.63,
      "换手率": 2.16
    },
    {
      "日期": "2025-04-10",
      "股票代码": "603016",
      "开盘": 25.31,
      "收盘": 25.86,
      "最高": 26.03,
      "最低": 24.41,
      "成交量": 26190,
      "成交额": 68304062.0,
      "振幅": 6.69,
      "涨跌幅": 6.82,
      "涨跌额": 1.65,
      "换手率": 1.77
    },
    {
      "日期": "2025-04-11",
      "股票代码": "603016",
      "开盘": 25.5,
      "收盘": 26.04,
      "最高": 26.29,
      "最低": 25.41,
      "成交量": 14638,
      "成交额": 38764380.0,
      "振幅": 3.4,
      "涨跌幅": 0.7,
      "涨跌额": 0.18,
      "换手率": 0.99
    },
    {
      "日期": "2025-04-14",
      "股票代码": "603016",
      "开盘": 26.16,
      "收盘": 26.04,
      "最高": 26.96,
      "最低": 25.93,
      "成交量": 21779,
      "成交额": 58701626.0,
      "振幅": 3.96,
      "涨跌幅": 0.0,
      "涨跌额": 0.0,
      "换手率": 1.47
    },
    {
      "日期": "2025-04-15",
      "股票代码": "603016",
      "开盘": 25.97,
      "收盘": 25.53,
      "最高": 26.14,
      "最低": 25.26,
      "成交量": 19438,
      "成交额": 50485200.0,
      "振幅": 3.38,
      "涨跌幅": -1.96,
      "涨跌额": -0.51,
      "换手率": 1.31
    },
    {
      "日期": "2025-04-16",
      "股票代码": "603016",
      "开盘": 25.72,
      "收盘": 25.15,
      "最高": 25.72,
      "最低": 24.54,
      "成交量": 11824,
      "成交额": 30252567.0,
      "振幅": 4.62,
      "涨跌幅": -1.49,
      "涨跌额": -0.38,
      "换手率": 0.8
    },
    {
      "日期": "2025-04-17",
      "股票代码": "603016",
      "开盘": 24.94,
      "收盘": 25.28,
      "最高": 25.63,
      "最低": 24.94,
      "成交量": 13301,
      "成交额": 34400260.0,
      "振幅": 2.74,
      "涨跌幅": 0.52,
      "涨跌额": 0.13,
      "换手率": 0.9
    },
    {
      "日期": "2025-04-18",
      "股票代码": "603016",
      "开盘": 25.26,
      "收盘": 25.48,
      "最高": 25.55,
      "最低": 24.81,
      "成交量": 11808,
      "成交额": 30266019.0,
      "振幅": 2.93,
      "涨跌幅": 0.79,
      "涨跌额": 0.2,
      "换手率": 0.8
    },
    {
      "日期": "2025-04-21",
      "股票代码": "603016",
      "开盘": 25.26,
      "收盘": 25.51,
      "最高": 25.62,
      "最低": 25.09,
      "成交量": 12450,
      "成交额": 32311617.0,
      "振幅": 2.08,
      "涨跌幅": 0.12,
      "涨跌额": 0.03,
      "换手率": 0.84
    },
    {
      "日期": "2025-04-22",
      "股票代码": "603016",
      "开盘": 25.43,
      "收盘": 25.2,
      "最高": 26.09,
      "最低": 25.14,
      "成交量": 13709,
      "成交额": 35656257.0,
      "振幅": 3.72,
      "涨跌幅": -1.22,
      "涨跌额": -0.31,
      "换手率": 0.93
    },
    {
      "日期": "2025-04-23",
      "股票代码": "603016",
      "开盘": 25.47,
      "收盘": 26.18,
      "最高": 26.33,
      "最低": 25.47,
      "成交量": 23749,
      "成交额": 62880649.0,
      "振幅": 3.41,
      "涨跌幅": 3.89,
      "涨跌额": 0.98,
      "换手率": 1.6
    },
    {
      "日期": "2025-04-24",
      "股票代码": "603016",
      "开盘": 25.87,
      "收盘": 26.02,
      "最高": 26.27,
      "最低": 25.34,
      "成交量": 15779,
      "成交额": 41548259.0,
      "振幅": 3.55,
      "涨跌幅": -0.61,
      "涨跌额": -0.16,
      "换手率": 1.06
    },
    {
      "日期": "2025-04-25",
      "股票代码": "603016",
      "开盘": 25.88,
      "收盘": 26.6,
      "最高": 27.61,
      "最低": 25.56,
      "成交量": 29916,
      "成交额": 81512375.0,
      "振幅": 7.88,
      "涨跌幅": 2.23,
      "涨跌额": 0.58,
      "换手率": 2.02
    },
    {
      "日期": "2025-04-28",
      "股票代码": "603016",
      "开盘": 26.47,
      "收盘": 25.52,
      "最高": 26.68,
      "最低": 25.51,
      "成交量": 20138,
      "成交额": 52955986.0,
      "振幅": 4.4,
      "涨跌幅": -4.06,
      "涨跌额": -1.08,
      "换手率": 1.36
    },
    {
      "日期": "2025-04-29",
      "股票代码": "603016",
      "开盘": 25.46,
      "收盘": 26.2,
      "最高": 26.68,
      "最低": 25.32,
      "成交量": 15037,
      "成交额": 40024048.0,
      "振幅": 5.33,
      "涨跌幅": 2.66,
      "涨跌额": 0.68,
      "换手率": 1.01
    },
    {
      "日期": "2025-04-30",
      "股票代码": "603016",
      "开盘": 26.53,
      "收盘": 26.54,
      "最高": 26.98,
      "最低": 26.06,
      "成交量": 11251,
      "成交额": 30567702.0,
      "振幅": 3.51,
      "涨跌幅": 1.3,
      "涨跌额": 0.34,
      "换手率": 0.76
    },
    {
      "日期": "2025-05-06",
      "股票代码": "603016",
      "开盘": 26.53,
      "收盘": 27.21,
      "最高": 27.21,
      "最低": 26.43,
      "成交量": 15226,
      "成交额": 41606258.0,
      "振幅": 2.94,
      "涨跌幅": 2.52,
      "涨跌额": 0.67,
      "换手率": 1.03
    },
    {
      "日期": "2025-05-07",
      "股票代码": "603016",
      "开盘": 27.36,
      "收盘": 28.11,
      "最高": 28.18,
      "最低": 27.3,
      "成交量": 20542,
      "成交额": 57958772.0,
      "振幅": 3.23,
      "涨跌幅": 3.31,
      "涨跌额": 0.9,
      "换手率": 1.39
    },
    {
      "日期": "2025-05-08",
      "股票代码": "603016",
      "开盘": 27.93,
      "收盘": 28.0,
      "最高": 28.4,
      "最低": 27.85,
      "成交量": 14468,
      "成交额": 41326093.0,
      "振幅": 1.96,
      "涨跌幅": -0.39,
      "涨跌额": -0.11,
      "换手率": 0.98
    },
    {
      "日期": "2025-05-09",
      "股票代码": "603016",
      "开盘": 28.0,
      "收盘": 27.54,
      "最高": 28.14,
      "最低": 27.35,
      "成交量": 12717,
      "成交额": 35655088.0,
      "振幅": 2.82,
      "涨跌幅": -1.64,
      "涨跌额": -0.46,
      "换手率": 0.86
    },
    {
      "日期": "2025-05-12",
      "股票代码": "603016",
      "开盘": 27.71,
      "收盘": 28.3,
      "最高": 29.19,
      "最低": 27.71,
      "成交量": 20978,
      "成交额": 60701019.0,
      "振幅": 5.37,
      "涨跌幅": 2.76,
      "涨跌额": 0.76,
      "换手率": 1.42
    },
    {
      "日期": "2025-05-13",
      "股票代码": "603016",
      "开盘": 28.54,
      "收盘": 28.77,
      "最高": 29.39,
      "最低": 28.19,
      "成交量": 26573,
      "成交额": 77708039.0,
      "振幅": 4.24,
      "涨跌幅": 1.66,
      "涨跌额": 0.47,
      "换手率": 1.79
    },
    {
      "日期": "2025-05-14",
      "股票代码": "603016",
      "开盘": 28.64,
      "收盘": 28.33,
      "最高": 28.91,
      "最低": 28.13,
      "成交量": 16159,
      "成交额": 46678356.0,
      "振幅": 2.71,
      "涨跌幅": -1.53,
      "涨跌额": -0.44,
      "换手率": 1.09
    },
    {
      "日期": "2025-05-15",
      "股票代码": "603016",
      "开盘": 27.93,
      "收盘": 28.61,
      "最高": 29.43,
      "最低": 27.75,
      "成交量": 31780,
      "成交额": 92645315.0,
      "振幅": 5.93,
      "涨跌幅": 0.99,
      "涨跌额": 0.28,
      "换手率": 2.14
    },
    {
      "日期": "2025-05-16",
      "股票代码": "603016",
      "开盘": 28.35,
      "收盘": 28.31,
      "最高": 29.11,
      "最低": 28.25,
      "成交量": 16775,
      "成交额": 48853202.0,
      "振幅": 3.01,
      "涨跌幅": -1.05,
      "涨跌额": -0.3,
      "换手率": 1.13
    },
    {
      "日期": "2025-05-19",
      "股票代码": "603016",
      "开盘": 29.93,
      "收盘": 31.19,
      "最高": 31.19,
      "最低": 28.84,
      "成交量": 46816,
      "成交额": 143344760.0,
      "振幅": 8.3,
      "涨跌幅": 10.17,
      "涨跌额": 2.88,
      "换手率": 3.16
    },
    {
      "日期": "2025-05-20",
      "股票代码": "603016",
      "开盘": 31.03,
      "收盘": 33.11,
      "最高": 34.01,
      "最低": 30.18,
      "成交量": 96885,
      "成交额": 316876525.0,
      "振幅": 12.28,
      "涨跌幅": 6.16,
      "涨跌额": 1.92,
      "换手率": 6.54
    },
    {
      "日期": "2025-05-21",
      "股票代码": "603016",
      "开盘": 32.19,
      "收盘": 32.83,
      "最高": 33.37,
      "最低": 31.63,
      "成交量": 64370,
      "成交额": 211031812.0,
      "振幅": 5.26,
      "涨跌幅": -0.85,
      "涨跌额": -0.28,
      "换手率": 4.34
    },
    {
      "日期": "2025-05-22",
      "股票代码": "603016",
      "开盘": 32.32,
      "收盘": 33.77,
      "最高": 33.9,
      "最低": 32.11,
      "成交量": 58346,
      "成交额": 196606422.0,
      "振幅": 5.45,
      "涨跌幅": 2.86,
      "涨跌额": 0.94,
      "换手率": 3.94
    },
    {
      "日期": "2025-05-23",
      "股票代码": "603016",
      "开盘": 33.34,
      "收盘": 33.02,
      "最高": 34.86,
      "最低": 32.98,
      "成交量": 60165,
      "成交额": 207522790.0,
      "振幅": 5.57,
      "涨跌幅": -2.22,
      "涨跌额": -0.75,
      "换手率": 4.06
    },
    {
      "日期": "2025-05-26",
      "股票代码": "603016",
      "开盘": 32.7,
      "收盘": 31.76,
      "最高": 32.7,
      "最低": 31.31,
      "成交量": 40923,
      "成交额": 131932570.0,
      "振幅": 4.21,
      "涨跌幅": -3.82,
      "涨跌额": -1.26,
      "换手率": 2.76
    },
    {
      "日期": "2025-05-27",
      "股票代码": "603016",
      "开盘": 31.53,
      "收盘": 31.53,
      "最高": 31.88,
      "最低": 31.11,
      "成交量": 26889,
      "成交额": 85860607.0,
      "振幅": 2.42,
      "涨跌幅": -0.72,
      "涨跌额": -0.23,
      "换手率": 1.81
    },
    {
      "日期": "2025-05-28",
      "股票代码": "603016",
      "开盘": 31.46,
      "收盘": 30.53,
      "最高": 31.58,
      "最低": 30.34,
      "成交量": 30479,
      "成交额": 95699630.0,
      "振幅": 3.93,
      "涨跌幅": -3.17,
      "涨跌额": -1.0,
      "换手率": 2.06
    },
    {
      "日期": "2025-05-29",
      "股票代码": "603016",
      "开盘": 30.55,
      "收盘": 31.23,
      "最高": 31.53,
      "最低": 30.23,
      "成交量": 25939,
      "成交额": 81480572.0,
      "振幅": 4.26,
      "涨跌幅": 2.29,
      "涨跌额": 0.7,
      "换手率": 1.75
    },
    {
      "日期": "2025-05-30",
      "股票代码": "603016",
      "开盘": 30.94,
      "收盘": 30.41,
      "最高": 31.83,
      "最低": 30.26,
      "成交量": 24075,
      "成交额": 75618819.0,
      "振幅": 5.03,
      "涨跌幅": -2.63,
      "涨跌额": -0.82,
      "换手率": 1.62
    },
    {
      "日期": "2025-06-03",
      "股票代码": "603016",
      "开盘": 30.34,
      "收盘": 30.67,
      "最高": 30.83,
      "最低": 29.74,
      "成交量": 20307,
      "成交额": 62605081.0,
      "振幅": 3.58,
      "涨跌幅": 0.85,
      "涨跌额": 0.26,
      "换手率": 1.37
    },
    {
      "日期": "2025-06-04",
      "股票代码": "603016",
      "开盘": 30.73,
      "收盘": 30.63,
      "最高": 30.92,
      "最低": 30.43,
      "成交量": 13737,
      "成交额": 42685972.0,
      "振幅": 1.6,
      "涨跌幅": -0.13,
      "涨跌额": -0.04,
      "换手率": 0.93
    },
    {
      "日期": "2025-06-05",
      "股票代码": "603016",
      "开盘": 30.66,
      "收盘": 30.13,
      "最高": 31.12,
      "最低": 30.13,
      "成交量": 19800,
      "成交额": 61292459.0,
      "振幅": 3.23,
      "涨跌幅": -1.63,
      "涨跌额": -0.5,
      "换手率": 1.34
    },
    {
      "日期": "2025-06-06",
      "股票代码": "603016",
      "开盘": 30.31,
      "收盘": 30.63,
      "最高": 30.7,
      "最低": 29.84,
      "成交量": 14189,
      "成交额": 43701792.0,
      "振幅": 2.85,
      "涨跌幅": 1.66,
      "涨跌额": 0.5,
      "换手率": 0.96
    },
    {
      "日期": "2025-06-09",
      "股票代码": "603016",
      "开盘": 30.51,
      "收盘": 31.13,
      "最高": 31.31,
      "最低": 30.33,
      "成交量": 20684,
      "成交额": 64724477.0,
      "振幅": 3.2,
      "涨跌幅": 1.63,
      "涨跌额": 0.5,
      "换手率": 1.4
    },
    {
      "日期": "2025-06-10",
      "股票代码": "603016",
      "开盘": 31.03,
      "收盘": 30.16,
      "最高": 31.12,
      "最低": 29.44,
      "成交量": 27034,
      "成交额": 82824463.0,
      "振幅": 5.4,
      "涨跌幅": -3.12,
      "涨跌额": -0.97,
      "换手率": 1.82
    },
    {
      "日期": "2025-06-11",
      "股票代码": "603016",
      "开盘": 30.03,
      "收盘": 30.6,
      "最高": 30.87,
      "最低": 30.03,
      "成交量": 14581,
      "成交额": 45097864.0,
      "振幅": 2.79,
      "涨跌幅": 1.46,
      "涨跌额": 0.44,
      "换手率": 0.98
    },
    {
      "日期": "2025-06-12",
      "股票代码": "603016",
      "开盘": 30.47,
      "收盘": 30.11,
      "最高": 30.61,
      "最低": 30.05,
      "成交量": 11569,
      "成交额": 35525685.0,
      "振幅": 1.83,
      "涨跌幅": -1.6,
      "涨跌额": -0.49,
      "换手率": 0.78
    },
    {
      "日期": "2025-06-13",
      "股票代码": "603016",
      "开盘": 30.11,
      "收盘": 29.48,
      "最高": 30.15,
      "最低": 29.23,
      "成交量": 12533,
      "成交额": 37652206.0,
      "振幅": 3.06,
      "涨跌幅": -2.09,
      "涨跌额": -0.63,
      "换手率": 0.85
    },
    {
      "日期": "2025-06-16",
      "股票代码": "603016",
      "开盘": 29.23,
      "收盘": 29.49,
      "最高": 29.71,
      "最低": 28.87,
      "成交量": 9051,
      "成交额": 27112756.0,
      "振幅": 2.85,
      "涨跌幅": 0.03,
      "涨跌额": 0.01,
      "换手率": 0.61
    },
    {
      "日期": "2025-06-17",
      "股票代码": "603016",
      "开盘": 29.43,
      "收盘": 29.06,
      "最高": 29.53,
      "最低": 28.91,
      "成交量": 10862,
      "成交额": 32163518.0,
      "振幅": 2.1,
      "涨跌幅": -1.46,
      "涨跌额": -0.43,
      "换手率": 0.73
    },
    {
      "日期": "2025-06-18",
      "股票代码": "603016",
      "开盘": 29.06,
      "收盘": 29.39,
      "最高": 29.5,
      "最低": 28.68,
      "成交量": 9298,
      "成交额": 27026182.0,
      "振幅": 2.82,
      "涨跌幅": 1.14,
      "涨跌额": 0.33,
      "换手率": 0.63
    },
    {
      "日期": "2025-06-19",
      "股票代码": "603016",
      "开盘": 29.39,
      "收盘": 28.76,
      "最高": 29.77,
      "最低": 28.58,
      "成交量": 12135,
      "成交额": 35394225.0,
      "振幅": 4.05,
      "涨跌幅": -2.14,
      "涨跌额": -0.63,
      "换手率": 0.82
    },
    {
      "日期": "2025-06-20",
      "股票代码": "603016",
      "开盘": 28.58,
      "收盘": 29.04,
      "最高": 29.1,
      "最低": 28.58,
      "成交量": 8580,
      "成交额": 24712236.0,
      "振幅": 1.81,
      "涨跌幅": 0.97,
      "涨跌额": 0.28,
      "换手率": 0.58
    },
    {
      "日期": "2025-06-23",
      "股票代码": "603016",
      "开盘": 28.6,
      "收盘": 29.04,
      "最高": 29.39,
      "最低": 28.51,
      "成交量": 14395,
      "成交额": 41496862.0,
      "振幅": 3.03,
      "涨跌幅": 0.0,
      "涨跌额": 0.0,
      "换手率": 0.97
    },
    {
      "日期": "2025-06-24",
      "股票代码": "603016",
      "开盘": 29.04,
      "收盘": 29.57,
      "最高": 29.7,
      "最低": 28.91,
      "成交量": 12294,
      "成交额": 36191248.0,
      "振幅": 2.72,
      "涨跌幅": 1.83,
      "涨跌额": 0.53,
      "换手率": 0.83
    },
    {
      "日期": "2025-06-25",
      "股票代码": "603016",
      "开盘": 29.6,
      "收盘": 29.85,
      "最高": 30.14,
      "最低": 29.48,
      "成交量": 15180,
      "成交额": 45145765.0,
      "振幅": 2.23,
      "涨跌幅": 0.95,
      "涨跌额": 0.28,
      "换手率": 1.02
    },
    {
      "日期": "2025-06-26",
      "股票代码": "603016",
      "开盘": 29.8,
      "收盘": 29.55,
      "最高": 30.07,
      "最低": 29.48,
      "成交量": 10836,
      "成交额": 32142338.0,
      "振幅": 1.98,
      "涨跌幅": -1.01,
      "涨跌额": -0.3,
      "换手率": 0.73
    },
    {
      "日期": "2025-06-27",
      "股票代码": "603016",
      "开盘": 29.63,
      "收盘": 29.79,
      "最高": 29.94,
      "最低": 29.08,
      "成交量": 11716,
      "成交额": 34637827.0,
      "振幅": 2.91,
      "涨跌幅": 0.81,
      "涨跌额": 0.24,
      "换手率": 0.79
    },
    {
      "日期": "2025-06-30",
      "股票代码": "603016",
      "开盘": 29.6,
      "收盘": 29.73,
      "最高": 29.76,
      "最低": 29.0,
      "成交量": 11860,
      "成交额": 35043346.0,
      "振幅": 2.55,
      "涨跌幅": -0.2,
      "涨跌额": -0.06,
      "换手率": 0.8
    },
    {
      "日期": "2025-07-01",
      "股票代码": "603016",
      "开盘": 29.72,
      "收盘": 30.57,
      "最高": 31.13,
      "最低": 29.31,
      "成交量": 29121,
      "成交额": 88965628.0,
      "振幅": 6.12,
      "涨跌幅": 2.83,
      "涨跌额": 0.84,
      "换手率": 1.97
    },
    {
      "日期": "2025-07-02",
      "股票代码": "603016",
      "开盘": 30.35,
      "收盘": 29.52,
      "最高": 30.57,
      "最低": 29.34,
      "成交量": 18701,
      "成交额": 55492289.0,
      "振幅": 4.02,
      "涨跌幅": -3.43,
      "涨跌额": -1.05,
      "换手率": 1.26
    },
    {
      "日期": "2025-07-03",
      "股票代码": "603016",
      "开盘": 29.66,
      "收盘": 29.55,
      "最高": 30.17,
      "最低": 29.49,
      "成交量": 12587,
      "成交额": 37455286.0,
      "振幅": 2.3,
      "涨跌幅": 0.1,
      "涨跌额": 0.03,
      "换手率": 0.85
    },
    {
      "日期": "2025-07-04",
      "股票代码": "603016",
      "开盘": 29.41,
      "收盘": 29.03,
      "最高": 29.55,
      "最低": 28.94,
      "成交量": 12812,
      "成交额": 37275664.0,
      "振幅": 2.06,
      "涨跌幅": -1.76,
      "涨跌额": -0.52,
      "换手率": 0.86
    },
    {
      "日期": "2025-07-07",
      "股票代码": "603016",
      "开盘": 28.86,
      "收盘": 29.14,
      "最高": 29.28,
      "最低": 28.86,
      "成交量": 9337,
      "成交额": 27093694.0,
      "振幅": 1.45,
      "涨跌幅": 0.38,
      "涨跌额": 0.11,
      "换手率": 0.63
    },
    {
      "日期": "2025-07-08",
      "股票代码": "603016",
      "开盘": 29.08,
      "收盘": 29.92,
      "最高": 30.1,
      "最低": 28.96,
      "成交量": 20957,
      "成交额": 62042592.0,
      "振幅": 3.91,
      "涨跌幅": 2.68,
      "涨跌额": 0.78,
      "换手率": 1.41
    },
    {
      "日期": "2025-07-09",
      "股票代码": "603016",
      "开盘": 29.9,
      "收盘": 29.68,
      "最高": 30.18,
      "最低": 29.56,
      "成交量": 11594,
      "成交额": 34652405.0,
      "振幅": 2.07,
      "涨跌幅": -0.8,
      "涨跌额": -0.24,
      "换手率": 0.78
    },
    {
      "日期": "2025-07-10",
      "股票代码": "603016",
      "开盘": 29.54,
      "收盘": 29.7,
      "最高": 29.84,
      "最低": 29.27,
      "成交量": 10320,
      "成交额": 30502734.0,
      "振幅": 1.92,
      "涨跌幅": 0.07,
      "涨跌额": 0.02,
      "换手率": 0.7
    },
    {
      "日期": "2025-07-11",
      "股票代码": "603016",
      "开盘": 29.7,
      "收盘": 29.67,
      "最高": 29.78,
      "最低": 29.17,
      "成交量": 10163,
      "成交额": 29906029.0,
      "振幅": 2.05,
      "涨跌幅": -0.1,
      "涨跌额": -0.03,
      "换手率": 0.69
    },
    {
      "日期": "2025-07-14",
      "股票代码": "603016",
      "开盘": 29.55,
      "收盘": 29.83,
      "最高": 30.16,
      "最低": 29.53,
      "成交量": 11792,
      "成交额": 35273500.0,
      "振幅": 2.12,
      "涨跌幅": 0.54,
      "涨跌额": 0.16,
      "换手率": 0.8
    },
    {
      "日期": "2025-07-15",
      "股票代码": "603016",
      "开盘": 29.74,
      "收盘": 29.61,
      "最高": 29.87,
      "最低": 29.3,
      "成交量": 10562,
      "成交额": 31145229.0,
      "振幅": 1.91,
      "涨跌幅": -0.74,
      "涨跌额": -0.22,
      "换手率": 0.71
    },
    {
      "日期": "2025-07-16",
      "股票代码": "603016",
      "开盘": 29.63,
      "收盘": 30.16,
      "最高": 30.63,
      "最低": 29.63,
      "成交量": 20898,
      "成交额": 63009163.0,
      "振幅": 3.38,
      "涨跌幅": 1.86,
      "涨跌额": 0.55,
      "换手率": 1.41
    },
    {
      "日期": "2025-07-17",
      "股票代码": "603016",
      "开盘": 30.16,
      "收盘": 30.21,
      "最高": 30.49,
      "最低": 29.9,
      "成交量": 13624,
      "成交额": 41048403.0,
      "振幅": 1.96,
      "涨跌幅": 0.17,
      "涨跌额": 0.05,
      "换手率": 0.92
    },
    {
      "日期": "2025-07-18",
      "股票代码": "603016",
      "开盘": 30.23,
      "收盘": 29.79,
      "最高": 30.23,
      "最低": 29.68,
      "成交量": 14172,
      "成交额": 42256246.0,
      "振幅": 1.82,
      "涨跌幅": -1.39,
      "涨跌额": -0.42,
      "换手率": 0.96
    },
    {
      "日期": "2025-07-21",
      "股票代码": "603016",
      "开盘": 29.71,
      "收盘": 30.47,
      "最高": 30.97,
      "最低": 29.56,
      "成交量": 29154,
      "成交额": 88043471.0,
      "振幅": 4.73,
      "涨跌幅": 2.28,
      "涨跌额": 0.68,
      "换手率": 1.97
    },
    {
      "日期": "2025-07-22",
      "股票代码": "603016",
      "开盘": 30.35,
      "收盘": 30.18,
      "最高": 30.6,
      "最低": 30.03,
      "成交量": 21155,
      "成交额": 64023701.0,
      "振幅": 1.87,
      "涨跌幅": -0.95,
      "涨跌额": -0.29,
      "换手率": 1.43
    },
    {
      "日期": "2025-07-23",
      "股票代码": "603016",
      "开盘": 30.17,
      "收盘": 28.75,
      "最高": 30.17,
      "最低": 28.74,
      "成交量": 37184,
      "成交额": 108808773.0,
      "振幅": 4.74,
      "涨跌幅": -4.74,
      "涨跌额": -1.43,
      "换手率": 2.51
    },
    {
      "日期": "2025-07-24",
      "股票代码": "603016",
      "开盘": 28.75,
      "收盘": 28.08,
      "最高": 28.95,
      "最低": 27.5,
      "成交量": 45524,
      "成交额": 128683724.0,
      "振幅": 5.04,
      "涨跌幅": -2.33,
      "涨跌额": -0.67,
      "换手率": 3.07
    },
    {
      "日期": "2025-07-25",
      "股票代码": "603016",
      "开盘": 28.1,
      "收盘": 28.48,
      "最高": 28.48,
      "最低": 27.8,
      "成交量": 18736,
      "成交额": 52901342.0,
      "振幅": 2.42,
      "涨跌幅": 1.42,
      "涨跌额": 0.4,
      "换手率": 1.26
    },
    {
      "日期": "2025-07-28",
      "股票代码": "603016",
      "开盘": 28.34,
      "收盘": 27.14,
      "最高": 28.43,
      "最低": 26.91,
      "成交量": 53709,
      "成交额": 147654301.0,
      "振幅": 5.34,
      "涨跌幅": -4.71,
      "涨跌额": -1.34,
      "换手率": 3.63
    },
    {
      "日期": "2025-07-29",
      "股票代码": "603016",
      "开盘": 27.34,
      "收盘": 27.32,
      "最高": 27.39,
      "最低": 27.08,
      "成交量": 17473,
      "成交额": 47589807.0,
      "振幅": 1.14,
      "涨跌幅": 0.66,
      "涨跌额": 0.18,
      "换手率": 1.18
    },
    {
      "日期": "2025-07-30",
      "股票代码": "603016",
      "开盘": 27.3,
      "收盘": 27.54,
      "最高": 27.58,
      "最低": 26.82,
      "成交量": 25646,
      "成交额": 69592020.0,
      "振幅": 2.78,
      "涨跌幅": 0.81,
      "涨跌额": 0.22,
      "换手率": 1.73
    },
    {
      "日期": "2025-07-31",
      "股票代码": "603016",
      "开盘": 27.38,
      "收盘": 26.77,
      "最高": 27.45,
      "最低": 26.62,
      "成交量": 31061,
      "成交额": 83699303.0,
      "振幅": 3.01,
      "涨跌幅": -2.8,
      "涨跌额": -0.77,
      "换手率": 2.1
    },
    {
      "日期": "2025-08-01",
      "股票代码": "603016",
      "开盘": 26.66,
      "收盘": 27.03,
      "最高": 27.12,
      "最低": 26.66,
      "成交量": 13292,
      "成交额": 35846610.0,
      "振幅": 1.72,
      "涨跌幅": 0.97,
      "涨跌额": 0.26,
      "换手率": 0.9
    },
    {
      "日期": "2025-08-04",
      "股票代码": "603016",
      "开盘": 27.08,
      "收盘": 26.92,
      "最高": 27.08,
      "最低": 26.65,
      "成交量": 12934,
      "成交额": 34811938.0,
      "振幅": 1.59,
      "涨跌幅": -0.41,
      "涨跌额": -0.11,
      "换手率": 0.87
    },
    {
      "日期": "2025-08-05",
      "股票代码": "603016",
      "开盘": 27.0,
      "收盘": 27.06,
      "最高": 27.13,
      "最低": 26.89,
      "成交量": 12885,
      "成交额": 34814866.0,
      "振幅": 0.89,
      "涨跌幅": 0.52,
      "涨跌额": 0.14,
      "换手率": 0.87
    },
    {
      "日期": "2025-08-06",
      "股票代码": "603016",
      "开盘": 27.05,
      "收盘": 27.35,
      "最高": 27.5,
      "最低": 26.85,
      "成交量": 17943,
      "成交额": 48911952.0,
      "振幅": 2.4,
      "涨跌幅": 1.07,
      "涨跌额": 0.29,
      "换手率": 1.21
    },
    {
      "日期": "2025-08-07",
      "股票代码": "603016",
      "开盘": 27.33,
      "收盘": 27.65,
      "最高": 28.28,
      "最低": 27.2,
      "成交量": 33689,
      "成交额": 93614749.0,
      "振幅": 3.95,
      "涨跌幅": 1.1,
      "涨跌额": 0.3,
      "换手率": 2.27
    },
    {
      "日期": "2025-08-08",
      "股票代码": "603016",
      "开盘": 27.34,
      "收盘": 26.96,
      "最高": 27.6,
      "最低": 26.89,
      "成交量": 28370,
      "成交额": 76962776.0,
      "振幅": 2.57,
      "涨跌幅": -2.5,
      "涨跌额": -0.69,
      "换手率": 1.91
    },
    {
      "日期": "2025-08-11",
      "股票代码": "603016",
      "开盘": 26.97,
      "收盘": 27.5,
      "最高": 27.62,
      "最低": 26.89,
      "成交量": 23938,
      "成交额": 65353121.0,
      "振幅": 2.71,
      "涨跌幅": 2.0,
      "涨跌额": 0.54,
      "换手率": 1.62
    },
    {
      "日期": "2025-08-12",
      "股票代码": "603016",
      "开盘": 27.48,
      "收盘": 27.6,
      "最高": 28.03,
      "最低": 27.22,
      "成交量": 25553,
      "成交额": 70794310.0,
      "振幅": 2.95,
      "涨跌幅": 0.36,
      "涨跌额": 0.1,
      "换手率": 1.72
    },
    {
      "日期": "2025-08-13",
      "股票代码": "603016",
      "开盘": 27.61,
      "收盘": 27.38,
      "最高": 27.7,
      "最低": 27.21,
      "成交量": 20441,
      "成交额": 55950238.0,
      "振幅": 1.78,
      "涨跌幅": -0.8,
      "涨跌额": -0.22,
      "换手率": 1.38
    },
    {
      "日期": "2025-08-14",
      "股票代码": "603016",
      "开盘": 27.39,
      "收盘": 27.09,
      "最高": 27.5,
      "最低": 27.02,
      "成交量": 22720,
      "成交额": 61847437.0,
      "振幅": 1.75,
      "涨跌幅": -1.06,
      "涨跌额": -0.29,
      "换手率": 1.53
    },
    {
      "日期": "2025-08-15",
      "股票代码": "603016",
      "开盘": 27.18,
      "收盘": 27.09,
      "最高": 27.29,
      "最低": 26.9,
      "成交量": 24210,
      "成交额": 65461416.0,
      "振幅": 1.44,
      "涨跌幅": 0.0,
      "涨跌额": 0.0,
      "换手率": 1.63
    },
    {
      "日期": "2025-08-18",
      "股票代码": "603016",
      "开盘": 27.2,
      "收盘": 27.18,
      "最高": 27.43,
      "最低": 27.03,
      "成交量": 32136,
      "成交额": 87442441.0,
      "振幅": 1.48,
      "涨跌幅": 0.33,
      "涨跌额": 0.09,
      "换手率": 2.17
    },
    {
      "日期": "2025-08-19",
      "股票代码": "603016",
      "开盘": 27.17,
      "收盘": 27.25,
      "最高": 27.49,
      "最低": 27.04,
      "成交量": 24803,
      "成交额": 67625239.0,
      "振幅": 1.66,
      "涨跌幅": 0.26,
      "涨跌额": 0.07,
      "换手率": 1.67
    },
    {
      "日期": "2025-08-20",
      "股票代码": "603016",
      "开盘": 27.22,
      "收盘": 28.1,
      "最高": 28.52,
      "最低": 27.06,
      "成交量": 56118,
      "成交额": 156761492.0,
      "振幅": 5.36,
      "涨跌幅": 3.12,
      "涨跌额": 0.85,
      "换手率": 3.79
    },
    {
      "日期": "2025-08-21",
      "股票代码": "603016",
      "开盘": 27.95,
      "收盘": 27.64,
      "最高": 28.16,
      "最低": 27.52,
      "成交量": 26086,
      "成交额": 72385137.0,
      "振幅": 2.28,
      "涨跌幅": -1.64,
      "涨跌额": -0.46,
      "换手率": 1.76
    },
    {
      "日期": "2025-08-22",
      "股票代码": "603016",
      "开盘": 27.53,
      "收盘": 27.71,
      "最高": 27.85,
      "最低": 27.42,
      "成交量": 20361,
      "成交额": 56156477.0,
      "振幅": 1.56,
      "涨跌幅": 0.25,
      "涨跌额": 0.07,
      "换手率": 1.37
    },
    {
      "日期": "2025-08-25",
      "股票代码": "603016",
      "开盘": 27.83,
      "收盘": 27.46,
      "最高": 27.85,
      "最低": 27.25,
      "成交量": 29373,
      "成交额": 80688416.0,
      "振幅": 2.17,
      "涨跌幅": -0.9,
      "涨跌额": -0.25,
      "换手率": 1.98
    },
    {
      "日期": "2025-08-26",
      "股票代码": "603016",
      "开盘": 27.5,
      "收盘": 27.93,
      "最高": 28.8,
      "最低": 27.41,
      "成交量": 48604,
      "成交额": 136967722.0,
      "振幅": 5.06,
      "涨跌幅": 1.71,
      "涨跌额": 0.47,
      "换手率": 3.28
    },
    {
      "日期": "2025-08-27",
      "股票代码": "603016",
      "开盘": 27.94,
      "收盘": 27.48,
      "最高": 28.17,
      "最低": 27.42,
      "成交量": 34137,
      "成交额": 94743618.0,
      "振幅": 2.69,
      "涨跌幅": -1.61,
      "涨跌额": -0.45,
      "换手率": 2.3
    },
    {
      "日期": "2025-08-28",
      "股票代码": "603016",
      "开盘": 27.4,
      "收盘": 26.77,
      "最高": 27.67,
      "最低": 26.0,
      "成交量": 45366,
      "成交额": 121316488.0,
      "振幅": 6.08,
      "涨跌幅": -2.58,
      "涨跌额": -0.71,
      "换手率": 3.06
    },
    {
      "日期": "2025-08-29",
      "股票代码": "603016",
      "开盘": 26.67,
      "收盘": 26.75,
      "最高": 26.96,
      "最低": 26.4,
      "成交量": 20299,
      "成交额": 54240360.0,
      "振幅": 2.09,
      "涨跌幅": -0.07,
      "涨跌额": -0.02,
      "换手率": 1.37
    },
    {
      "日期": "2025-09-01",
      "股票代码": "603016",
      "开盘": 26.71,
      "收盘": 26.76,
      "最高": 27.12,
      "最低": 26.17,
      "成交量": 19800,
      "成交额": 52868536.0,
      "振幅": 3.55,
      "涨跌幅": 0.04,
      "涨跌额": 0.01,
      "换手率": 1.34
    },
    {
      "日期": "2025-09-02",
      "股票代码": "603016",
      "开盘": 26.63,
      "收盘": 26.47,
      "最高": 26.95,
      "最低": 26.11,
      "成交量": 20513,
      "成交额": 54003600.0,
      "振幅": 3.14,
      "涨跌幅": -1.08,
      "涨跌额": -0.29,
      "换手率": 1.38
    },
    {
      "日期": "2025-09-03",
      "股票代码": "603016",
      "开盘": 26.32,
      "收盘": 26.01,
      "最高": 26.72,
      "最低": 26.0,
      "成交量": 16454,
      "成交额": 43134717.0,
      "振幅": 2.72,
      "涨跌幅": -1.74,
      "涨跌额": -0.46,
      "换手率": 1.11
    },
    {
      "日期": "2025-09-04",
      "股票代码": "603016",
      "开盘": 26.03,
      "收盘": 26.08,
      "最高": 26.44,
      "最低": 25.8,
      "成交量": 23152,
      "成交额": 60582376.0,
      "振幅": 2.46,
      "涨跌幅": 0.27,
      "涨跌额": 0.07,
      "换手率": 1.56
    },
    {
      "日期": "2025-09-05",
      "股票代码": "603016",
      "开盘": 26.3,
      "收盘": 26.6,
      "最高": 26.75,
      "最低": 26.08,
      "成交量": 21635,
      "成交额": 57367595.0,
      "振幅": 2.57,
      "涨跌幅": 1.99,
      "涨跌额": 0.52,
      "换手率": 1.46
    },
    {
      "日期": "2025-09-08",
      "股票代码": "603016",
      "开盘": 26.6,
      "收盘": 27.98,
      "最高": 28.0,
      "最低": 26.6,
      "成交量": 46524,
      "成交额": 127770950.0,
      "振幅": 5.26,
      "涨跌幅": 5.19,
      "涨跌额": 1.38,
      "换手率": 3.14
    },
    {
      "日期": "2025-09-09",
      "股票代码": "603016",
      "开盘": 27.97,
      "收盘": 27.58,
      "最高": 27.97,
      "最低": 27.18,
      "成交量": 25011,
      "成交额": 68852473.0,
      "振幅": 2.82,
      "涨跌幅": -1.43,
      "涨跌额": -0.4,
      "换手率": 1.69
    },
    {
      "日期": "2025-09-10",
      "股票代码": "603016",
      "开盘": 27.56,
      "收盘": 27.63,
      "最高": 27.7,
      "最低": 27.24,
      "成交量": 18746,
      "成交额": 51476926.0,
      "振幅": 1.67,
      "涨跌幅": 0.18,
      "涨跌额": 0.05,
      "换手率": 1.27
    },
    {
      "日期": "2025-09-11",
      "股票代码": "603016",
      "开盘": 27.63,
      "收盘": 27.6,
      "最高": 28.19,
      "最低": 27.2,
      "成交量": 35040,
      "成交额": 97143602.0,
      "振幅": 3.58,
      "涨跌幅": -0.11,
      "涨跌额": -0.03,
      "换手率": 2.37
    },
    {
      "日期": "2025-09-12",
      "股票代码": "603016",
      "开盘": 27.6,
      "收盘": 27.38,
      "最高": 27.99,
      "最低": 27.25,
      "成交量": 26383,
      "成交额": 72724491.0,
      "振幅": 2.68,
      "涨跌幅": -0.8,
      "涨跌额": -0.22,
      "换手率": 1.78
    },
    {
      "日期": "2025-09-15",
      "股票代码": "603016",
      "开盘": 27.48,
      "收盘": 27.14,
      "最高": 27.48,
      "最低": 26.9,
      "成交量": 21857,
      "成交额": 59222332.0,
      "振幅": 2.12,
      "涨跌幅": -0.88,
      "涨跌额": -0.24,
      "换手率": 1.48
    },
    {
      "日期": "2025-09-16",
      "股票代码": "603016",
      "开盘": 26.96,
      "收盘": 27.18,
      "最高": 27.38,
      "最低": 26.9,
      "成交量": 17416,
      "成交额": 47270875.0,
      "振幅": 1.77,
      "涨跌幅": 0.15,
      "涨跌额": 0.04,
      "换手率": 1.18
    },
    {
      "日期": "2025-09-17",
      "股票代码": "603016",
      "开盘": 27.3,
      "收盘": 27.07,
      "最高": 27.8,
      "最低": 27.01,
      "成交量": 22627,
      "成交额": 61717554.0,
      "振幅": 2.91,
      "涨跌幅": -0.4,
      "涨跌额": -0.11,
      "换手率": 1.53
    },
    {
      "日期": "2025-09-18",
      "股票代码": "603016",
      "开盘": 27.08,
      "收盘": 29.78,
      "最高": 29.78,
      "最低": 27.08,
      "成交量": 107411,
      "成交额": 309567699.0,
      "振幅": 9.97,
      "涨跌幅": 10.01,
      "涨跌额": 2.71,
      "换手率": 7.25
    },
    {
      "日期": "2025-09-19",
      "股票代码": "603016",
      "开盘": 30.02,
      "收盘": 29.5,
      "最高": 30.61,
      "最低": 29.1,
      "成交量": 90625,
      "成交额": 270380997.0,
      "振幅": 5.07,
      "涨跌幅": -0.94,
      "涨跌额": -0.28,
      "换手率": 6.12
    },
    {
      "日期": "2025-09-22",
      "股票代码": "603016",
      "开盘": 29.61,
      "收盘": 29.48,
      "最高": 29.9,
      "最低": 28.93,
      "成交量": 41120,
      "成交额": 120623139.0,
      "振幅": 3.29,
      "涨跌幅": -0.07,
      "涨跌额": -0.02,
      "换手率": 2.78
    },
    {
      "日期": "2025-09-23",
      "股票代码": "603016",
      "开盘": 29.56,
      "收盘": 28.79,
      "最高": 29.56,
      "最低": 27.59,
      "成交量": 50168,
      "成交额": 142539597.0,
      "振幅": 6.68,
      "涨跌幅": -2.34,
      "涨跌额": -0.69,
      "换手率": 3.39
    },
    {
      "日期": "2025-09-24",
      "股票代码": "603016",
      "开盘": 28.56,
      "收盘": 28.57,
      "最高": 28.68,
      "最低": 28.13,
      "成交量": 30221,
      "成交额": 85862360.0,
      "振幅": 1.91,
      "涨跌幅": -0.76,
      "涨跌额": -0.22,
      "换手率": 2.04
    },
    {
      "日期": "2025-09-25",
      "股票代码": "603016",
      "开盘": 28.57,
      "收盘": 28.23,
      "最高": 29.12,
      "最低": 28.11,
      "成交量": 42040,
      "成交额": 119987782.0,
      "振幅": 3.54,
      "涨跌幅": -1.19,
      "涨跌额": -0.34,
      "换手率": 2.84
    },
    {
      "日期": "2025-09-26",
      "股票代码": "603016",
      "开盘": 28.02,
      "收盘": 28.25,
      "最高": 28.49,
      "最低": 27.9,
      "成交量": 24191,
      "成交额": 68367076.0,
      "振幅": 2.09,
      "涨跌幅": 0.07,
      "涨跌额": 0.02,
      "换手率": 1.63
    },
    {
      "日期": "2025-09-29",
      "股票代码": "603016",
      "开盘": 28.25,
      "收盘": 28.44,
      "最高": 29.11,
      "最低": 27.5,
      "成交量": 38246,
      "成交额": 108316254.0,
      "振幅": 5.7,
      "涨跌幅": 0.67,
      "涨跌额": 0.19,
      "换手率": 2.58
    },
    {
      "日期": "2025-09-30",
      "股票代码": "603016",
      "开盘": 28.35,
      "收盘": 28.02,
      "最高": 28.87,
      "最低": 27.95,
      "成交量": 26539,
      "成交额": 74991494.0,
      "振幅": 3.23,
      "涨跌幅": -1.48,
      "涨跌额": -0.42,
      "换手率": 1.79
    },
    {
      "日期": "2025-10-09",
      "股票代码": "603016",
      "开盘": 28.2,
      "收盘": 28.49,
      "最高": 29.0,
      "最低": 27.69,
      "成交量": 37198,
      "成交额": 105760185.0,
      "振幅": 4.68,
      "涨跌幅": 1.68,
      "涨跌额": 0.47,
      "换手率": 2.51
    },
    {
      "日期": "2025-10-10",
      "股票代码": "603016",
      "开盘": 28.36,
      "收盘": 29.19,
      "最高": 29.2,
      "最低": 28.13,
      "成交量": 43297,
      "成交额": 124897046.0,
      "振幅": 3.76,
      "涨跌幅": 2.46,
      "涨跌额": 0.7,
      "换手率": 2.92
    },
    {
      "日期": "2025-10-13",
      "股票代码": "603016",
      "开盘": 26.5,
      "收盘": 27.18,
      "最高": 27.7,
      "最低": 26.45,
      "成交量": 60777,
      "成交额": 165136150.0,
      "振幅": 4.28,
      "涨跌幅": -6.89,
      "涨跌额": -2.01,
      "换手率": 4.1
    },
    {
      "日期": "2025-10-14",
      "股票代码": "603016",
      "开盘": 27.32,
      "收盘": 25.88,
      "最高": 27.48,
      "最低": 25.71,
      "成交量": 47895,
      "成交额": 127057694.0,
      "振幅": 6.51,
      "涨跌幅": -4.78,
      "涨跌额": -1.3,
      "换手率": 3.23
    },
    {
      "日期": "2025-10-15",
      "股票代码": "603016",
      "开盘": 25.5,
      "收盘": 26.1,
      "最高": 26.15,
      "最低": 25.38,
      "成交量": 25462,
      "成交额": 65553546.0,
      "振幅": 2.98,
      "涨跌幅": 0.85,
      "涨跌额": 0.22,
      "换手率": 1.72
    },
    {
      "日期": "2025-10-16",
      "股票代码": "603016",
      "开盘": 26.09,
      "收盘": 25.69,
      "最高": 26.35,
      "最低": 25.56,
      "成交量": 18721,
      "成交额": 48407275.0,
      "振幅": 3.03,
      "涨跌幅": -1.57,
      "涨跌额": -0.41,
      "换手率": 1.26
    },
    {
      "日期": "2025-10-17",
      "股票代码": "603016",
      "开盘": 25.6,
      "收盘": 24.25,
      "最高": 25.69,
      "最低": 24.2,
      "成交量": 34118,
      "成交额": 84762526.0,
      "振幅": 5.8,
      "涨跌幅": -5.61,
      "涨跌额": -1.44,
      "换手率": 2.3
    },
    {
      "日期": "2025-10-20",
      "股票代码": "603016",
      "开盘": 24.24,
      "收盘": 24.77,
      "最高": 25.02,
      "最低": 24.24,
      "成交量": 19803,
      "成交额": 48881616.0,
      "振幅": 3.22,
      "涨跌幅": 2.14,
      "涨跌额": 0.52,
      "换手率": 1.34
    },
    {
      "日期": "2025-10-21",
      "股票代码": "603016",
      "开盘": 24.8,
      "收盘": 25.22,
      "最高": 25.24,
      "最低": 24.72,
      "成交量": 14080,
      "成交额": 35265052.0,
      "振幅": 2.1,
      "涨跌幅": 1.82,
      "涨跌额": 0.45,
      "换手率": 0.95
    },
    {
      "日期": "2025-10-22",
      "股票代码": "603016",
      "开盘": 25.21,
      "收盘": 25.17,
      "最高": 25.39,
      "最低": 25.0,
      "成交量": 10705,
      "成交额": 26987865.0,
      "振幅": 1.55,
      "涨跌幅": -0.2,
      "涨跌额": -0.05,
      "换手率": 0.72
    },
    {
      "日期": "2025-10-23",
      "股票代码": "603016",
      "开盘": 25.34,
      "收盘": 25.86,
      "最高": 25.96,
      "最低": 24.97,
      "成交量": 19082,
      "成交额": 48808572.0,
      "振幅": 3.93,
      "涨跌幅": 2.74,
      "涨跌额": 0.69,
      "换手率": 1.29
    },
    {
      "日期": "2025-10-24",
      "股票代码": "603016",
      "开盘": 25.86,
      "收盘": 25.74,
      "最高": 26.04,
      "最低": 25.61,
      "成交量": 13061,
      "成交额": 33646366.0,
      "振幅": 1.66,
      "涨跌幅": -0.46,
      "涨跌额": -0.12,
      "换手率": 0.88
    },
    {
      "日期": "2025-10-27",
      "股票代码": "603016",
      "开盘": 25.86,
      "收盘": 26.12,
      "最高": 26.48,
      "最低": 25.75,
      "成交量": 20522,
      "成交额": 53433142.0,
      "振幅": 2.84,
      "涨跌幅": 1.48,
      "涨跌额": 0.38,
      "换手率": 1.39
    },
    {
      "日期": "2025-10-28",
      "股票代码": "603016",
      "开盘": 25.99,
      "收盘": 26.5,
      "最高": 27.16,
      "最低": 25.85,
      "成交量": 29585,
      "成交额": 78774585.0,
      "振幅": 5.02,
      "涨跌幅": 1.45,
      "涨跌额": 0.38,
      "换手率": 2.0
    },
    {
      "日期": "2025-10-29",
      "股票代码": "603016",
      "开盘": 26.5,
      "收盘": 26.79,
      "最高": 27.18,
      "最低": 26.31,
      "成交量": 25710,
      "成交额": 69103059.0,
      "振幅": 3.28,
      "涨跌幅": 1.09,
      "涨跌额": 0.29,
      "换手率": 1.74
    },
    {
      "日期": "2025-10-30",
      "股票代码": "603016",
      "开盘": 26.79,
      "收盘": 25.96,
      "最高": 27.0,
      "最低": 25.93,
      "成交量": 22699,
      "成交额": 59523053.0,
      "振幅": 3.99,
      "涨跌幅": -3.1,
      "涨跌额": -0.83,
      "换手率": 1.53
    },
    {
      "日期": "2025-10-31",
      "股票代码": "603016",
      "开盘": 25.87,
      "收盘": 26.21,
      "最高": 26.44,
      "最低": 25.87,
      "成交量": 12344,
      "成交额": 32426017.0,
      "振幅": 2.2,
      "涨跌幅": 0.96,
      "涨跌额": 0.25,
      "换手率": 0.83
    },
    {
      "日期": "2025-11-03",
      "股票代码": "603016",
      "开盘": 26.23,
      "收盘": 26.97,
      "最高": 27.3,
      "最低": 26.11,
      "成交量": 30955,
      "成交额": 83049838.0,
      "振幅": 4.54,
      "涨跌幅": 2.9,
      "涨跌额": 0.76,
      "换手率": 2.09
    },
    {
      "日期": "2025-11-04",
      "股票代码": "603016",
      "开盘": 27.18,
      "收盘": 26.76,
      "最高": 27.28,
      "最低": 26.66,
      "成交量": 15388,
      "成交额": 41367250.0,
      "振幅": 2.3,
      "涨跌幅": -0.78,
      "涨跌额": -0.21,
      "换手率": 1.04
    },
    {
      "日期": "2025-11-05",
      "股票代码": "603016",
      "开盘": 26.74,
      "收盘": 27.13,
      "最高": 27.27,
      "最低": 26.51,
      "成交量": 23107,
      "成交额": 62360671.0,
      "振幅": 2.84,
      "涨跌幅": 1.38,
      "涨跌额": 0.37,
      "换手率": 1.56
    },
    {
      "日期": "2025-11-06",
      "股票代码": "603016",
      "开盘": 27.3,
      "收盘": 26.97,
      "最高": 27.3,
      "最低": 26.85,
      "成交量": 16961,
      "成交额": 45884740.0,
      "振幅": 1.66,
      "涨跌幅": -0.59,
      "涨跌额": -0.16,
      "换手率": 1.14
    },
    {
      "日期": "2025-11-07",
      "股票代码": "603016",
      "开盘": 26.92,
      "收盘": 26.68,
      "最高": 27.13,
      "最低": 26.6,
      "成交量": 15257,
      "成交额": 40907312.0,
      "振幅": 1.97,
      "涨跌幅": -1.08,
      "涨跌额": -0.29,
      "换手率": 1.03
    },
    {
      "日期": "2025-11-10",
      "股票代码": "603016",
      "开盘": 26.61,
      "收盘": 26.43,
      "最高": 26.78,
      "最低": 26.31,
      "成交量": 15775,
      "成交额": 41767621.0,
      "振幅": 1.76,
      "涨跌幅": -0.94,
      "涨跌额": -0.25,
      "换手率": 1.06
    },
    {
      "日期": "2025-11-11",
      "股票代码": "603016",
      "开盘": 26.44,
      "收盘": 26.67,
      "最高": 27.09,
      "最低": 26.44,
      "成交量": 14242,
      "成交额": 38212187.0,
      "振幅": 2.46,
      "涨跌幅": 0.91,
      "涨跌额": 0.24,
      "换手率": 0.96
    },
    {
      "日期": "2025-11-12",
      "股票代码": "603016",
      "开盘": 26.7,
      "收盘": 26.1,
      "最高": 26.7,
      "最低": 25.99,
      "成交量": 15848,
      "成交额": 41583462.0,
      "振幅": 2.66,
      "涨跌幅": -2.14,
      "涨跌额": -0.57,
      "换手率": 1.07
    },
    {
      "日期": "2025-11-13",
      "股票代码": "603016",
      "开盘": 26.13,
      "收盘": 26.07,
      "最高": 26.35,
      "最低": 26.0,
      "成交量": 11731,
      "成交额": 30683856.0,
      "振幅": 1.34,
      "涨跌幅": -0.11,
      "涨跌额": -0.03,
      "换手率": 0.79
    },
    {
      "日期": "2025-11-14",
      "股票代码": "603016",
      "开盘": 26.02,
      "收盘": 26.1,
      "最高": 26.44,
      "最低": 25.88,
      "成交量": 13185,
      "成交额": 34406611.0,
      "振幅": 2.15,
      "涨跌幅": 0.12,
      "涨跌额": 0.03,
      "换手率": 0.89
    },
    {
      "日期": "2025-11-17",
      "股票代码": "603016",
      "开盘": 26.23,
      "收盘": 26.28,
      "最高": 26.78,
      "最低": 25.81,
      "成交量": 15139,
      "成交额": 39719244.0,
      "振幅": 3.72,
      "涨跌幅": 0.69,
      "涨跌额": 0.18,
      "换手率": 1.02
    },
    {
      "日期": "2025-11-18",
      "股票代码": "603016",
      "开盘": 26.25,
      "收盘": 25.77,
      "最高": 26.25,
      "最低": 25.73,
      "成交量": 13198,
      "成交额": 34192506.0,
      "振幅": 1.98,
      "涨跌幅": -1.94,
      "涨跌额": -0.51,
      "换手率": 0.89
    },
    {
      "日期": "2025-11-19",
      "股票代码": "603016",
      "开盘": 25.79,
      "收盘": 25.45,
      "最高": 25.89,
      "最低": 25.2,
      "成交量": 15049,
      "成交额": 38368513.0,
      "振幅": 2.68,
      "涨跌幅": -1.24,
      "涨跌额": -0.32,
      "换手率": 1.02
    },
    {
      "日期": "2025-11-20",
      "股票代码": "603016",
      "开盘": 25.76,
      "收盘": 25.22,
      "最高": 25.81,
      "最低": 25.15,
      "成交量": 9149,
      "成交额": 23255213.0,
      "振幅": 2.59,
      "涨跌幅": -0.9,
      "涨跌额": -0.23,
      "换手率": 0.62
    },
    {
      "日期": "2025-11-21",
      "股票代码": "603016",
      "开盘": 25.1,
      "收盘": 24.74,
      "最高": 25.65,
      "最低": 24.6,
      "成交量": 17757,
      "成交额": 44376626.0,
      "振幅": 4.16,
      "涨跌幅": -1.9,
      "涨跌额": -0.48,
      "换手率": 1.2
    },
    {
      "日期": "2025-11-24",
      "股票代码": "603016",
      "开盘": 24.8,
      "收盘": 24.96,
      "最高": 25.12,
      "最低": 24.61,
      "成交量": 13476,
      "成交额": 33452943.0,
      "振幅": 2.06,
      "涨跌幅": 0.89,
      "涨跌额": 0.22,
      "换手率": 0.91
    },
    {
      "日期": "2025-11-25",
      "股票代码": "603016",
      "开盘": 25.01,
      "收盘": 25.04,
      "最高": 25.44,
      "最低": 24.92,
      "成交量": 11138,
      "成交额": 28036863.0,
      "振幅": 2.08,
      "涨跌幅": 0.32,
      "涨跌额": 0.08,
      "换手率": 0.75
    },
    {
      "日期": "2025-11-26",
      "股票代码": "603016",
      "开盘": 25.08,
      "收盘": 24.74,
      "最高": 25.2,
      "最低": 24.7,
      "成交量": 10581,
      "成交额": 26328435.0,
      "振幅": 2.0,
      "涨跌幅": -1.2,
      "涨跌额": -0.3,
      "换手率": 0.71
    },
    {
      "日期": "2025-11-27",
      "股票代码": "603016",
      "开盘": 24.76,
      "收盘": 25.19,
      "最高": 25.74,
      "最低": 24.69,
      "成交量": 16381,
      "成交额": 41247925.0,
      "振幅": 4.24,
      "涨跌幅": 1.82,
      "涨跌额": 0.45,
      "换手率": 1.11
    },
    {
      "日期": "2025-11-28",
      "股票代码": "603016",
      "开盘": 25.18,
      "收盘": 26.62,
      "最高": 26.88,
      "最低": 24.86,
      "成交量": 41245,
      "成交额": 108329908.0,
      "振幅": 8.02,
      "涨跌幅": 5.68,
      "涨跌额": 1.43,
      "换手率": 2.78
    },
    {
      "日期": "2025-12-01",
      "股票代码": "603016",
      "开盘": 26.62,
      "收盘": 26.77,
      "最高": 27.15,
      "最低": 26.5,
      "成交量": 30431,
      "成交额": 81515212.0,
      "振幅": 2.44,
      "涨跌幅": 0.56,
      "涨跌额": 0.15,
      "换手率": 2.05
    },
    {
      "日期": "2025-12-02",
      "股票代码": "603016",
      "开盘": 26.77,
      "收盘": 26.56,
      "最高": 26.8,
      "最低": 26.42,
      "成交量": 12624,
      "成交额": 33546447.0,
      "振幅": 1.42,
      "涨跌幅": -0.78,
      "涨跌额": -0.21,
      "换手率": 0.85
    },
    {
      "日期": "2025-12-03",
      "股票代码": "603016",
      "开盘": 26.71,
      "收盘": 26.45,
      "最高": 26.84,
      "最低": 26.42,
      "成交量": 9854,
      "成交额": 26120188.0,
      "振幅": 1.58,
      "涨跌幅": -0.41,
      "涨跌额": -0.11,
      "换手率": 0.67
    },
    {
      "日期": "2025-12-04",
      "股票代码": "603016",
      "开盘": 26.38,
      "收盘": 25.78,
      "最高": 26.6,
      "最低": 25.75,
      "成交量": 14493,
      "成交额": 37699533.0,
      "振幅": 3.21,
      "涨跌幅": -2.53,
      "涨跌额": -0.67,
      "换手率": 0.98
    },
    {
      "日期": "2025-12-05",
      "股票代码": "603016",
      "开盘": 25.77,
      "收盘": 25.82,
      "最高": 25.87,
      "最低": 25.32,
      "成交量": 9393,
      "成交额": 24073333.0,
      "振幅": 2.13,
      "涨跌幅": 0.16,
      "涨跌额": 0.04,
      "换手率": 0.63
    },
    {
      "日期": "2025-12-08",
      "股票代码": "603016",
      "开盘": 25.92,
      "收盘": 26.02,
      "最高": 26.17,
      "最低": 25.52,
      "成交量": 13602,
      "成交额": 35176197.0,
      "振幅": 2.52,
      "涨跌幅": 0.77,
      "涨跌额": 0.2,
      "换手率": 0.92
    },
    {
      "日期": "2025-12-09",
      "股票代码": "603016",
      "开盘": 25.89,
      "收盘": 26.07,
      "最高": 26.46,
      "最低": 25.89,
      "成交量": 11633,
      "成交额": 30378882.0,
      "振幅": 2.19,
      "涨跌幅": 0.19,
      "涨跌额": 0.05,
      "换手率": 0.79
    },
    {
      "日期": "2025-12-10",
      "股票代码": "603016",
      "开盘": 26.02,
      "收盘": 26.36,
      "最高": 26.55,
      "最低": 25.92,
      "成交量": 16806,
      "成交额": 44135167.0,
      "振幅": 2.42,
      "涨跌幅": 1.11,
      "涨跌额": 0.29,
      "换手率": 1.13
    },
    {
      "日期": "2025-12-11",
      "股票代码": "603016",
      "开盘": 26.5,
      "收盘": 26.58,
      "最高": 26.93,
      "最低": 26.13,
      "成交量": 23968,
      "成交额": 63755797.0,
      "振幅": 3.03,
      "涨跌幅": 0.83,
      "涨跌额": 0.22,
      "换手率": 1.62
    },
    {
      "日期": "2025-12-12",
      "股票代码": "603016",
      "开盘": 26.58,
      "收盘": 27.05,
      "最高": 27.88,
      "最低": 26.39,
      "成交量": 57236,
      "成交额": 156367172.0,
      "振幅": 5.61,
      "涨跌幅": 1.77,
      "涨跌额": 0.47,
      "换手率": 3.86
    },
    {
      "日期": "2025-12-15",
      "股票代码": "603016",
      "开盘": 27.1,
      "收盘": 26.68,
      "最高": 27.15,
      "最低": 26.45,
      "成交量": 25241,
      "成交额": 67602531.0,
      "振幅": 2.59,
      "涨跌幅": -1.37,
      "涨跌额": -0.37,
      "换手率": 1.7
    },
    {
      "日期": "2025-12-16",
      "股票代码": "603016",
      "开盘": 26.5,
      "收盘": 26.9,
      "最高": 27.45,
      "最低": 26.35,
      "成交量": 22105,
      "成交额": 59362071.0,
      "振幅": 4.12,
      "涨跌幅": 0.82,
      "涨跌额": 0.22,
      "换手率": 1.49
    },
    {
      "日期": "2025-12-17",
      "股票代码": "603016",
      "开盘": 26.66,
      "收盘": 26.6,
      "最高": 26.91,
      "最低": 26.06,
      "成交量": 21785,
      "成交额": 57633909.0,
      "振幅": 3.16,
      "涨跌幅": -1.12,
      "涨跌额": -0.3,
      "换手率": 1.47
    },
    {
      "日期": "2025-12-18",
      "股票代码": "603016",
      "开盘": 26.59,
      "收盘": 26.97,
      "最高": 27.29,
      "最低": 26.44,
      "成交量": 16130,
      "成交额": 43579340.0,
      "振幅": 3.2,
      "涨跌幅": 1.39,
      "涨跌额": 0.37,
      "换手率": 1.09
    },
    {
      "日期": "2025-12-19",
      "股票代码": "603016",
      "开盘": 26.98,
      "收盘": 27.04,
      "最高": 27.17,
      "最低": 26.88,
      "成交量": 11930,
      "成交额": 32238097.0,
      "振幅": 1.08,
      "涨跌幅": 0.26,
      "涨跌额": 0.07,
      "换手率": 0.81
    },
    {
      "日期": "2025-12-22",
      "股票代码": "603016",
      "开盘": 27.0,
      "收盘": 27.1,
      "最高": 27.18,
      "最低": 26.8,
      "成交量": 13720,
      "成交额": 37067377.0,
      "振幅": 1.41,
      "涨跌幅": 0.22,
      "涨跌额": 0.06,
      "换手率": 0.93
    },
    {
      "日期": "2025-12-23",
      "股票代码": "603016",
      "开盘": 26.92,
      "收盘": 27.23,
      "最高": 27.82,
      "最低": 26.88,
      "成交量": 22796,
      "成交额": 62295843.0,
      "振幅": 3.47,
      "涨跌幅": 0.48,
      "涨跌额": 0.13,
      "换手率": 1.54
    },
    {
      "日期": "2025-12-24",
      "股票代码": "603016",
      "开盘": 27.23,
      "收盘": 27.58,
      "最高": 27.84,
      "最低": 27.2,
      "成交量": 27350,
      "成交额": 75500301.0,
      "振幅": 2.35,
      "涨跌幅": 1.29,
      "涨跌额": 0.35,
      "换手率": 1.85
    },
    {
      "日期": "2025-12-25",
      "股票代码": "603016",
      "开盘": 27.56,
      "收盘": 28.7,
      "最高": 28.97,
      "最低": 27.31,
      "成交量": 61321,
      "成交额": 174045155.0,
      "振幅": 6.02,
      "涨跌幅": 4.06,
      "涨跌额": 1.12,
      "换手率": 4.14
    },
    {
      "日期": "2025-12-26",
      "股票代码": "603016",
      "开盘": 28.7,
      "收盘": 28.8,
      "最高": 29.27,
      "最低": 28.51,
      "成交量": 48370,
      "成交额": 139789518.0,
      "振幅": 2.65,
      "涨跌幅": 0.35,
      "涨跌额": 0.1,
      "换手率": 3.26
    },
    {
      "日期": "2025-12-29",
      "股票代码": "603016",
      "开盘": 28.95,
      "收盘": 29.31,
      "最高": 29.59,
      "最低": 28.52,
      "成交量": 42188,
      "成交额": 123423044.0,
      "振幅": 3.72,
      "涨跌幅": 1.77,
      "涨跌额": 0.51,
      "换手率": 2.85
    },
    {
      "日期": "2025-12-30",
      "股票代码": "603016",
      "开盘": 29.59,
      "收盘": 29.22,
      "最高": 30.0,
      "最低": 29.0,
      "成交量": 38209,
      "成交额": 112444220.0,
      "振幅": 3.41,
      "涨跌幅": -0.31,
      "涨跌额": -0.09,
      "换手率": 2.58
    },
    {
      "日期": "2025-12-31",
      "股票代码": "603016",
      "开盘": 29.2,
      "收盘": 30.12,
      "最高": 30.5,
      "最低": 28.62,
      "成交量": 40174,
      "成交额": 118874388.0,
      "振幅": 6.43,
      "涨跌幅": 3.08,
      "涨跌额": 0.9,
      "换手率": 2.71
    },
    {
      "日期": "2026-01-05",
      "股票代码": "603016",
      "开盘": 30.12,
      "收盘": 30.09,
      "最高": 31.1,
      "最低": 29.84,
      "成交量": 38130,
      "成交额": 116222579.0,
      "振幅": 4.18,
      "涨跌幅": -0.1,
      "涨跌额": -0.03,
      "换手率": 2.57
    },
    {
      "日期": "2026-01-06",
      "股票代码": "603016",
      "开盘": 30.25,
      "收盘": 30.2,
      "最高": 30.5,
      "最低": 29.81,
      "成交量": 29312,
      "成交额": 88231696.0,
      "振幅": 2.29,
      "涨跌幅": 0.37,
      "涨跌额": 0.11,
      "换手率": 1.98
    },
    {
      "日期": "2026-01-07",
      "股票代码": "603016",
      "开盘": 30.0,
      "收盘": 30.91,
      "最高": 31.45,
      "最低": 29.98,
      "成交量": 35285,
      "成交额": 108726200.0,
      "振幅": 4.87,
      "涨跌幅": 2.35,
      "涨跌额": 0.71,
      "换手率": 2.38
    },
    {
      "日期": "2026-01-08",
      "股票代码": "603016",
      "开盘": 30.91,
      "收盘": 30.6,
      "最高": 30.97,
      "最低": 30.38,
      "成交量": 25792,
      "成交额": 79008283.0,
      "振幅": 1.91,
      "涨跌幅": -1.0,
      "涨跌额": -0.31,
      "换手率": 1.74
    },
    {
      "日期": "2026-01-09",
      "股票代码": "603016",
      "开盘": 30.35,
      "收盘": 30.28,
      "最高": 31.4,
      "最低": 30.1,
      "成交量": 35659,
      "成交额": 109604158.0,
      "振幅": 4.25,
      "涨跌幅": -1.05,
      "涨跌额": -0.32,
      "换手率": 2.41
    },
    {
      "日期": "2026-01-12",
      "股票代码": "603016",
      "开盘": 30.48,
      "收盘": 30.34,
      "最高": 30.55,
      "最低": 29.66,
      "成交量": 38750,
      "成交额": 117092695.0,
      "振幅": 2.94,
      "涨跌幅": 0.2,
      "涨跌额": 0.06,
      "换手率": 2.62
    },
    {
      "日期": "2026-01-13",
      "股票代码": "603016",
      "开盘": 30.28,
      "收盘": 30.57,
      "最高": 30.8,
      "最低": 29.45,
      "成交量": 35395,
      "成交额": 107253623.0,
      "振幅": 4.45,
      "涨跌幅": 0.76,
      "涨跌额": 0.23,
      "换手率": 2.39
    },
    {
      "日期": "2026-01-14",
      "股票代码": "603016",
      "开盘": 30.43,
      "收盘": 30.98,
      "最高": 31.45,
      "最低": 30.36,
      "成交量": 33871,
      "成交额": 104658269.0,
      "振幅": 3.57,
      "涨跌幅": 1.34,
      "涨跌额": 0.41,
      "换手率": 2.29
    },
    {
      "日期": "2026-01-15",
      "股票代码": "603016",
      "开盘": 30.68,
      "收盘": 31.39,
      "最高": 31.68,
      "最低": 30.48,
      "成交量": 27090,
      "成交额": 84685246.0,
      "振幅": 3.87,
      "涨跌幅": 1.32,
      "涨跌额": 0.41,
      "换手率": 1.83
    },
    {
      "日期": "2026-01-16",
      "股票代码": "603016",
      "开盘": 31.57,
      "收盘": 31.33,
      "最高": 31.98,
      "最低": 30.97,
      "成交量": 27466,
      "成交额": 86074981.0,
      "振幅": 3.22,
      "涨跌幅": -0.19,
      "涨跌额": -0.06,
      "换手率": 1.85
    },
    {
      "日期": "2026-01-19",
      "股票代码": "603016",
      "开盘": 31.44,
      "收盘": 30.81,
      "最高": 31.44,
      "最低": 30.58,
      "成交量": 27361,
      "成交额": 84725534.0,
      "振幅": 2.74,
      "涨跌幅": -1.66,
      "涨跌额": -0.52,
      "换手率": 1.85
    },
    {
      "日期": "2026-01-20",
      "股票代码": "603016",
      "开盘": 30.6,
      "收盘": 31.15,
      "最高": 31.81,
      "最低": 30.6,
      "成交量": 30461,
      "成交额": 95441372.0,
      "振幅": 3.93,
      "涨跌幅": 1.1,
      "涨跌额": 0.34,
      "换手率": 2.06
    },
    {
      "日期": "2026-01-21",
      "股票代码": "603016",
      "开盘": 31.13,
      "收盘": 32.63,
      "最高": 33.27,
      "最低": 30.8,
      "成交量": 36484,
      "成交额": 117635111.0,
      "振幅": 7.93,
      "涨跌幅": 4.75,
      "涨跌额": 1.48,
      "换手率": 2.46
    },
    {
      "日期": "2026-01-22",
      "股票代码": "603016",
      "开盘": 32.56,
      "收盘": 31.88,
      "最高": 32.6,
      "最低": 31.78,
      "成交量": 26017,
      "成交额": 83370471.0,
      "振幅": 2.51,
      "涨跌幅": -2.3,
      "涨跌额": -0.75,
      "换手率": 1.76
    },
    {
      "日期": "2026-01-23",
      "股票代码": "603016",
      "开盘": 31.86,
      "收盘": 32.49,
      "最高": 32.85,
      "最低": 31.69,
      "成交量": 20653,
      "成交额": 66905610.0,
      "振幅": 3.64,
      "涨跌幅": 1.91,
      "涨跌额": 0.61,
      "换手率": 1.39
    },
    {
      "日期": "2026-01-26",
      "股票代码": "603016",
      "开盘": 32.49,
      "收盘": 32.61,
      "最高": 33.37,
      "最低": 32.0,
      "成交量": 27156,
      "成交额": 89084281.0,
      "振幅": 4.22,
      "涨跌幅": 0.37,
      "涨跌额": 0.12,
      "换手率": 1.83
    },
    {
      "日期": "2026-01-27",
      "股票代码": "603016",
      "开盘": 32.65,
      "收盘": 31.7,
      "最高": 32.65,
      "最低": 31.28,
      "成交量": 28827,
      "成交额": 91358357.0,
      "振幅": 4.2,
      "涨跌幅": -2.79,
      "涨跌额": -0.91,
      "换手率": 1.95
    },
    {
      "日期": "2026-01-28",
      "股票代码": "603016",
      "开盘": 31.57,
      "收盘": 31.46,
      "最高": 32.13,
      "最低": 31.28,
      "成交量": 19422,
      "成交额": 61468986.0,
      "振幅": 2.68,
      "涨跌幅": -0.76,
      "涨跌额": -0.24,
      "换手率": 1.31
    },
    {
      "日期": "2026-01-29",
      "股票代码": "603016",
      "开盘": 31.36,
      "收盘": 30.96,
      "最高": 31.9,
      "最低": 30.82,
      "成交量": 17383,
      "成交额": 54376049.0,
      "振幅": 3.43,
      "涨跌幅": -1.59,
      "涨跌额": -0.5,
      "换手率": 1.17
    },
    {
      "日期": "2026-01-30",
      "股票代码": "603016",
      "开盘": 30.96,
      "收盘": 31.21,
      "最高": 31.39,
      "最低": 30.44,
      "成交量": 19665,
      "成交额": 60720018.0,
      "振幅": 3.07,
      "涨跌幅": 0.81,
      "涨跌额": 0.25,
      "换手率": 1.33
    },
    {
      "日期": "2026-02-02",
      "股票代码": "603016",
      "开盘": 31.14,
      "收盘": 31.13,
      "最高": 31.95,
      "最低": 31.0,
      "成交量": 23339,
      "成交额": 73612198.0,
      "振幅": 3.04,
      "涨跌幅": -0.26,
      "涨跌额": -0.08,
      "换手率": 1.58
    },
    {
      "日期": "2026-02-03",
      "股票代码": "603016",
      "开盘": 31.13,
      "收盘": 31.8,
      "最高": 31.85,
      "最低": 30.85,
      "成交量": 16322,
      "成交额": 51295454.0,
      "振幅": 3.21,
      "涨跌幅": 2.15,
      "涨跌额": 0.67,
      "换手率": 1.1
    },
    {
      "日期": "2026-02-04",
      "股票代码": "603016",
      "开盘": 31.78,
      "收盘": 31.33,
      "最高": 31.88,
      "最低": 31.1,
      "成交量": 22475,
      "成交额": 70703125.0,
      "振幅": 2.45,
      "涨跌幅": -1.48,
      "涨跌额": -0.47,
      "换手率": 1.52
    },
    {
      "日期": "2026-02-05",
      "股票代码": "603016",
      "开盘": 31.05,
      "收盘": 33.27,
      "最高": 33.84,
      "最低": 30.8,
      "成交量": 52599,
      "成交额": 170506094.0,
      "振幅": 9.7,
      "涨跌幅": 6.19,
      "涨跌额": 1.94,
      "换手率": 3.55
    },
    {
      "日期": "2026-02-06",
      "股票代码": "603016",
      "开盘": 33.33,
      "收盘": 35.5,
      "最高": 35.98,
      "最低": 33.29,
      "成交量": 66156,
      "成交额": 228843048.0,
      "振幅": 8.09,
      "涨跌幅": 6.7,
      "涨跌额": 2.23,
      "换手率": 4.47
    },
    {
      "日期": "2026-02-09",
      "股票代码": "603016",
      "开盘": 35.51,
      "收盘": 35.42,
      "最高": 36.0,
      "最低": 34.78,
      "成交量": 51319,
      "成交额": 181495640.0,
      "振幅": 3.44,
      "涨跌幅": -0.23,
      "涨跌额": -0.08,
      "换手率": 3.46
    },
    {
      "日期": "2026-02-10",
      "股票代码": "603016",
      "开盘": 35.42,
      "收盘": 34.7,
      "最高": 35.98,
      "最低": 34.6,
      "成交量": 30127,
      "成交额": 105585799.0,
      "振幅": 3.9,
      "涨跌幅": -2.03,
      "涨跌额": -0.72,
      "换手率": 2.03
    },
    {
      "日期": "2026-02-11",
      "股票代码": "603016",
      "开盘": 34.7,
      "收盘": 33.76,
      "最高": 34.8,
      "最低": 33.62,
      "成交量": 27735,
      "成交额": 94235576.0,
      "振幅": 3.4,
      "涨跌幅": -2.71,
      "涨跌额": -0.94,
      "换手率": 1.87
    },
    {
      "日期": "2026-02-12",
      "股票代码": "603016",
      "开盘": 34.0,
      "收盘": 33.79,
      "最高": 34.43,
      "最低": 33.44,
      "成交量": 24736,
      "成交额": 83931761.0,
      "振幅": 2.93,
      "涨跌幅": 0.09,
      "涨跌额": 0.03,
      "换手率": 1.67
    },
    {
      "日期": "2026-02-13",
      "股票代码": "603016",
      "开盘": 34.0,
      "收盘": 33.44,
      "最高": 34.15,
      "最低": 33.21,
      "成交量": 14339,
      "成交额": 48023905.0,
      "振幅": 2.78,
      "涨跌幅": -1.04,
      "涨跌额": -0.35,
      "换手率": 0.97
    },
    {
      "日期": "2026-02-24",
      "股票代码": "603016",
      "开盘": 33.83,
      "收盘": 33.4,
      "最高": 34.0,
      "最低": 33.02,
      "成交量": 23122,
      "成交额": 77181630.0,
      "振幅": 2.93,
      "涨跌幅": -0.12,
      "涨跌额": -0.04,
      "换手率": 1.56
    },
    {
      "日期": "2026-02-25",
      "股票代码": "603016",
      "开盘": 33.36,
      "收盘": 33.74,
      "最高": 34.11,
      "最低": 32.78,
      "成交量": 32095,
      "成交额": 107402436.0,
      "振幅": 3.98,
      "涨跌幅": 1.02,
      "涨跌额": 0.34,
      "换手率": 2.17
    },
    {
      "日期": "2026-02-26",
      "股票代码": "603016",
      "开盘": 33.59,
      "收盘": 33.75,
      "最高": 33.98,
      "最低": 33.32,
      "成交量": 16230,
      "成交额": 54558639.0,
      "振幅": 1.96,
      "涨跌幅": 0.03,
      "涨跌额": 0.01,
      "换手率": 1.1
    },
    {
      "日期": "2026-02-27",
      "股票代码": "603016",
      "开盘": 33.6,
      "收盘": 34.5,
      "最高": 34.75,
      "最低": 33.15,
      "成交量": 21895,
      "成交额": 74904766.0,
      "振幅": 4.74,
      "涨跌幅": 2.22,
      "涨跌额": 0.75,
      "换手率": 1.48
    },
    {
      "日期": "2026-03-02",
      "股票代码": "603016",
      "开盘": 33.98,
      "收盘": 32.17,
      "最高": 34.22,
      "最低": 32.1,
      "成交量": 42357,
      "成交额": 138663753.0,
      "振幅": 6.14,
      "涨跌幅": -6.75,
      "涨跌额": -2.33,
      "换手率": 2.86
    },
    {
      "日期": "2026-03-03",
      "股票代码": "603016",
      "开盘": 32.25,
      "收盘": 30.88,
      "最高": 32.66,
      "最低": 30.8,
      "成交量": 33452,
      "成交额": 105956570.0,
      "振幅": 5.78,
      "涨跌幅": -4.01,
      "涨跌额": -1.29,
      "换手率": 2.26
    },
    {
      "日期": "2026-03-04",
      "股票代码": "603016",
      "开盘": 30.86,
      "收盘": 31.07,
      "最高": 31.47,
      "最低": 30.0,
      "成交量": 21148,
      "成交额": 65500832.0,
      "振幅": 4.76,
      "涨跌幅": 0.62,
      "涨跌额": 0.19,
      "换手率": 1.43
    },
    {
      "日期": "2026-03-05",
      "股票代码": "603016",
      "开盘": 32.5,
      "收盘": 31.51,
      "最高": 32.57,
      "最低": 31.39,
      "成交量": 19500,
      "成交额": 62006368.0,
      "振幅": 3.8,
      "涨跌幅": 1.42,
      "涨跌额": 0.44,
      "换手率": 1.32
    },
    {
      "日期": "2026-03-06",
      "股票代码": "603016",
      "开盘": 31.05,
      "收盘": 33.16,
      "最高": 34.18,
      "最低": 31.05,
      "成交量": 34633,
      "成交额": 114257765.0,
      "振幅": 9.93,
      "涨跌幅": 5.24,
      "涨跌额": 1.65,
      "换手率": 2.34
    },
    {
      "日期": "2026-03-09",
      "股票代码": "603016",
      "开盘": 32.5,
      "收盘": 32.85,
      "最高": 33.12,
      "最低": 32.08,
      "成交量": 21116,
      "成交额": 68739438.0,
      "振幅": 3.14,
      "涨跌幅": -0.93,
      "涨跌额": -0.31,
      "换手率": 1.43
    },
    {
      "日期": "2026-03-10",
      "股票代码": "603016",
      "开盘": 33.3,
      "收盘": 33.85,
      "最高": 34.09,
      "最低": 32.92,
      "成交量": 19581,
      "成交额": 66130935.0,
      "振幅": 3.56,
      "涨跌幅": 3.04,
      "涨跌额": 1.0,
      "换手率": 1.32
    },
    {
      "日期": "2026-03-11",
      "股票代码": "603016",
      "开盘": 33.85,
      "收盘": 33.53,
      "最高": 34.51,
      "最低": 33.47,
      "成交量": 22794,
      "成交额": 77219689.0,
      "振幅": 3.07,
      "涨跌幅": -0.95,
      "涨跌额": -0.32,
      "换手率": 1.54
    },
    {
      "日期": "2026-03-12",
      "股票代码": "603016",
      "开盘": 33.37,
      "收盘": 32.34,
      "最高": 33.58,
      "最低": 32.23,
      "成交量": 17786,
      "成交额": 58267104.0,
      "振幅": 4.03,
      "涨跌幅": -3.55,
      "涨跌额": -1.19,
      "换手率": 1.2
    },
    {
      "日期": "2026-03-13",
      "股票代码": "603016",
      "开盘": 32.37,
      "收盘": 31.93,
      "最高": 32.66,
      "最低": 31.75,
      "成交量": 15401,
      "成交额": 49520571.0,
      "振幅": 2.81,
      "涨跌幅": -1.27,
      "涨跌额": -0.41,
      "换手率": 1.04
    },
    {
      "日期": "2026-03-16",
      "股票代码": "603016",
      "开盘": 32.86,
      "收盘": 31.99,
      "最高": 32.86,
      "最低": 31.38,
      "成交量": 21560,
      "成交额": 68671862.0,
      "振幅": 4.64,
      "涨跌幅": 0.19,
      "涨跌额": 0.06,
      "换手率": 1.46
    },
    {
      "日期": "2026-03-17",
      "股票代码": "603016",
      "开盘": 31.36,
      "收盘": 31.48,
      "最高": 32.13,
      "最低": 31.3,
      "成交量": 20052,
      "成交额": 63406526.0,
      "振幅": 2.59,
      "涨跌幅": -1.59,
      "涨跌额": -0.51,
      "换手率": 1.35
    },
    {
      "日期": "2026-03-18",
      "股票代码": "603016",
      "开盘": 31.82,
      "收盘": 34.63,
      "最高": 34.63,
      "最低": 31.25,
      "成交量": 48690,
      "成交额": 162804909.0,
      "振幅": 10.74,
      "涨跌幅": 10.01,
      "涨跌额": 3.15,
      "换手率": 3.29
    },
    {
      "日期": "2026-03-19",
      "股票代码": "603016",
      "开盘": 34.69,
      "收盘": 35.98,
      "最高": 37.0,
      "最低": 34.29,
      "成交量": 85755,
      "成交额": 308643175.0,
      "振幅": 7.83,
      "涨跌幅": 3.9,
      "涨跌额": 1.35,
      "换手率": 5.79
    },
    {
      "日期": "2026-03-20",
      "股票代码": "603016",
      "开盘": 35.95,
      "收盘": 35.07,
      "最高": 36.37,
      "最低": 34.97,
      "成交量": 52592,
      "成交额": 186738129.0,
      "振幅": 3.89,
      "涨跌幅": -2.53,
      "涨跌额": -0.91,
      "换手率": 3.55
    },
    {
      "日期": "2026-03-23",
      "股票代码": "603016",
      "开盘": 34.68,
      "收盘": 38.58,
      "最高": 38.58,
      "最低": 34.49,
      "成交量": 105733,
      "成交额": 395557258.0,
      "振幅": 11.66,
      "涨跌幅": 10.01,
      "涨跌额": 3.51,
      "换手率": 7.14
    },
    {
      "日期": "2026-03-24",
      "股票代码": "603016",
      "开盘": 39.15,
      "收盘": 39.69,
      "最高": 39.98,
      "最低": 37.95,
      "成交量": 99944,
      "成交额": 387711884.0,
      "振幅": 5.26,
      "涨跌幅": 2.88,
      "涨跌额": 1.11,
      "换手率": 6.75
    },
    {
      "日期": "2026-03-25",
      "股票代码": "603016",
      "开盘": 39.3,
      "收盘": 38.79,
      "最高": 39.4,
      "最低": 37.88,
      "成交量": 79063,
      "成交额": 303736554.0,
      "振幅": 3.83,
      "涨跌幅": -2.27,
      "涨跌额": -0.9,
      "换手率": 5.34
    },
    {
      "日期": "2026-03-26",
      "股票代码": "603016",
      "开盘": 38.41,
      "收盘": 41.0,
      "最高": 42.65,
      "最低": 38.08,
      "成交量": 91978,
      "成交额": 369911759.0,
      "振幅": 11.78,
      "涨跌幅": 5.7,
      "涨跌额": 2.21,
      "换手率": 6.21
    },
    {
      "日期": "2026-03-27",
      "股票代码": "603016",
      "开盘": 39.16,
      "收盘": 40.93,
      "最高": 42.61,
      "最低": 39.16,
      "成交量": 63912,
      "成交额": 260926220.0,
      "振幅": 8.41,
      "涨跌幅": -0.17,
      "涨跌额": -0.07,
      "换手率": 4.31
    }
  ],
  "update_time": "2026-03-28T01:26:56.009161"
}